README.rst
setup.py
tbzuploader/__init__.py
tbzuploader/console_scripts.py
tbzuploader/utils.py
tbzuploader.egg-info/PKG-INFO
tbzuploader.egg-info/SOURCES.txt
tbzuploader.egg-info/dependency_links.txt
tbzuploader.egg-info/entry_points.txt
tbzuploader.egg-info/not-zip-safe
tbzuploader.egg-info/requires.txt
tbzuploader.egg-info/top_level.txt
tbzuploader/tests/__init__.py
tbzuploader/tests/test_console_scripts.py
tbzuploader/tests/test_setup.py
tbzuploader/tests/test_utils.py