Metadata-Version: 1.0
Name: tbzuploader
Version: 2019.27.0
Summary: UNKNOWN
Home-page: https://github.com/tbz-pariv/tbzuploader
Author: TBZ-PARIV GmbH
Author-email: info@tbz-pariv.de
License: Apache Software License 2.0
Platform: UNKNOWN
